Lab1/johnsonCounter.v
module johnsonCounter(clk, reset, count);
   input clk, reset;
   output reg [3:0] count;

   integer ps, ns;
      
   always @ (posedge clk)
      if (~reset)
         ps <= 0;
      else
         case (ps)
         0: begin
               ps = 1;
               count = 4'b0000;
            end
         1: begin
               ps = 2;
               count = 4'b1000;
               end
         2: begin
               ps = 3;
               count = 4'b1100;
            end
         3: begin
               ps = 4;
               count = 4'b1110;
            end
         4: begin
               ps = 5;
               count = 4'b1111;
            end
         5: begin
               ps = 6;
               count = 4'b0111;
            end
         6: begin
               ps = 7;
               count = 4'b0011;
            end
         7: begin
               ps = 0;
               count = 4'b0001;
            end
      endcase

endmodule

DFlipFlop.v
module DFlipFlop(clk, reset, D, q, qBar);
   input D, clk, reset;
   output q, qBar;
   reg q;

   not n1 (qBar, q);

   always @ (negedge reset or posedge clk)
      begin
         if(!reset)
            q = 0;
         else
            q = D;
      end
endmodule

Lab 1/rippleCounter.v
//`include "DFlipFlop.v"

// A four stage (4 bit) ripple up (asynchronous) counter, with active low reset.
//a. Design the counter using a gate or structural model.
//b. Use the D flip-flop model in the adjacent listing.
module rippleCounter(clk, reset, count);
   input clk, reset;
   output [3:0] count;
   wire   [3:0] countbar;
	
   DFlipFlop bit0(.clk(clk), .reset(reset), .D(countbar[0]), .q(count[0]), .qBar(countbar[0]));
   DFlipFlop bit1(.clk(countbar[0]), .reset(reset), .D(countbar[1]), .q(count[1]), .qBar(countbar[1]));
   DFlipFlop bit2(.clk(countbar[1]), .reset(reset), .D(countbar[2]), .q(count[2]), .qBar(countbar[2]));
   DFlipFlop bit3(.clk(countbar[2]), .reset(reset), .D(countbar[3]), .q(count[3]), .qBar(countbar[3]));

endmodule

Lab 1/DE1_SoC.v
`include "rippleCounter.v"
`include "johnsonCounter.v"

module DE1_SoC (CLOCK_50, HEX0, HEX1, HEX2, HEX3, HEX4, HEX5, KEY, LEDR,
SW); 
	input 		 CLOCK_50; // 50MHz clock.
	input  [3:0] KEY; // True when not pressed, False when pressed
	input  [9:0] SW;	
	output [6:0] HEX0, HEX1, HEX2, HEX3, HEX4, HEX5;
	output [9:0] LEDR;
	
	// Generate clk off of CLOCK_50, whichClock picks rate.
	wire [31:0] clk;
	parameter whichClock = 25;
	clock_divider cdiv (CLOCK_50, clk);

endmodule
		
	//	A four stage (4 bit) synchronous Johnson up counter, with active low reset
		//a. Design the counter using a behavioural model.
		
	// A four stage (4 bit) synchronous up counter, with active low reset, using schematic entry.	
 

//divided_clocks[0] = 25MHz, [1] = 12.5Mhz, ... [23] = 3Hz, [24] = 1.5Hz,[25] = 0.75Hz, ...
module clock_divider (clock, divided_clocks);
	input clock;
	output reg [31:0] divided_clocks;
	
	initial
		divided_clocks <= 0;
	always @(posedge clock)
		divided_clocks <= divided_clocks + 1;
endmodule

module counterTestBench;
	wire clk, reset;
	wire[3:0] rippleCount, johnsonCount;
	
	rippleCounter rCounter (clk, reset, rippleCount);
	//syncroCounter synCounter (clk, reset, syncroCount);
	johnsonCounter jCounter (clk, reset, johnsonCount);
	
	Tester test(rippleCount, johnsonCount, clk, reset);
	
	
	initial begin
		$dumpfile("counterTesterLog.vcd");
		$dumpvars;
	end
endmodule
	
module Tester(rippleCount, johnsonCount, clk, reset);
	input [3:0] rippleCount, johnsonCount;
	output clk, reset;
	reg clk, reset;
	
	initial begin
		$display("\t\t clk \t reset \t rippleCount \t johnsonCount");
		$monitor("\t\t %b  \t %b    \t %b          \t %b", clk, reset, rippleCount, johnsonCount);
	end
	
	parameter CLOCK = 100;
	
	initial begin
		clk <= 0;
		forever #(CLOCK/2) clk <= ~clk;
	end

	initial begin @(posedge clk)
		reset <= 0; @(posedge clk)@(posedge clk)
		reset <= 1; @(posedge clk)@(posedge clk)
		repeat(30)@(posedge clk);
		$stop;
	end
	

endmodule

Lab 1/counterTesterLog.vcd
$date
	Thu Apr 13 14:25:54 2017
$end
$version
	Icarus Verilog
$end
$timescale
	1s
$end
$scope module DE1_SoC $end
$var wire 1 ! CLOCK_50 $end
$var wire 7 " HEX0 [6:0] $end
$var wire 7 # HEX1 [6:0] $end
$var wire 7 $ HEX2 [6:0] $end
$var wire 7 % HEX3 [6:0] $end
$var wire 7 & HEX4 [6:0] $end
$var wire 7 ' HEX5 [6:0] $end
$var wire 4 ( KEY [3:0] $end
$var wire 10 ) LEDR [9:0] $end
$var wire 10 * SW [9:0] $end
$var wire 32 + clk [31:0] $end
$scope module cdiv $end
$var wire 1 ! clock $end
$var reg 32 , divided_clocks [31:0] $end
$upscope $end
$upscope $end
$scope module counterTestBench $end
$var wire 1 - clk $end
$var wire 4 . johnsonCount [3:0] $end
$var wire 1 / reset $end
$var wire 4 0 rippleCount [3:0] $end
$scope module rCounter $end
$var wire 1 - clk $end
$var wire 4 1 count [3:0] $end
$var wire 4 2 countbar [3:0] $end
$var wire 1 / reset $end
$scope module bit0 $end
$var wire 1 3 D $end
$var wire 1 - clk $end
$var wire 1 4 qBar $end
$var wire 1 / reset $end
$var reg 1 5 q $end
$upscope $end
$scope module bit1 $end
$var wire 1 6 D $end
$var wire 1 7 clk $end
$var wire 1 8 qBar $end
$var wire 1 / reset $end
$var reg 1 9 q $end
$upscope $end
$scope module bit2 $end
$var wire 1 : D $end
$var wire 1 ; clk $end
$var wire 1 < qBar $end
$var wire 1 / reset $end
$var reg 1 = q $end
$upscope $end
$scope module bit3 $end
$var wire 1 > D $end
$var wire 1 ? clk $end
$var wire 1 @ qBar $end
$var wire 1 / reset $end
$var reg 1 A q $end
$upscope $end
$upscope $end
$scope module jCounter $end
$var wire 1 - clk $end
$var wire 1 / reset $end
$var reg 4 B count [3:0] $end
$var integer 32 C ps [31:0] $end
$upscope $end
$scope module test $end
$var wire 4 D johnsonCount [3:0] $end
$var wire 4 E rippleCount [3:0] $end
$var reg 1 F clk $end
$var reg 1 G reset $end
$upscope $end
$upscope $end
$enddefinitions $end
#0
$dumpvars
xG
0F
bx E
bx D
bx C
bx B
xA
x@
x?
x>
x=
x<
x;
x:
x9
x8
x7
x6
x5
x4
x3
bx 2
bx 1
bx 0
x/
bx .
0-
b0 ,
b0 +
bz *
bz )
bz (
bz '
bz &
bz %
bz $
bz #
bz "
z!
$end
#50
1>
1:
1?
16
1;
13
17
1@
1<
18
14
b1111 2
0A
0=
09
05
b0 0
b0 1
b0 E
0G
0/
1F
1-
#100
0F
0-
#150
b0 C
1F
1-
#200
0F
0-
#250
1G
1/
1F
1-
#300
0F
0-
#350
03
07
04
b1110 2
b0 B
b0 .
b0 D
b1 C
15
b1 0
b1 1
b1 E
1F
1-
#400
0F
0-
#450
06
0;
08
19
13
17
14
b1101 2
b1000 B
b1000 .
b1000 D
b10 C
05
b10 0
b10 1
b10 E
1F
1-
#500
0F
0-
#550
03
07
04
b1100 2
b1100 B
b1100 .
b1100 D
b11 C
15
b11 0
b11 1
b11 E
1F
1-
#600
0F
0-
#650
0:
0?
0<
1=
16
1;
18
09
13
17
14
b1011 2
b1110 B
b1110 .
b1110 D
b100 C
05
b100 0
b100 1
b100 E
1F
1-
#700
0F
0-
#750
03
07
04
b1010 2
b1111 B
b1111 .
b1111 D
b101 C
15
b101 0
b101 1
b101 E
1F
1-
#800
0F
0-
#850
06
0;
08
19
13
17
14
b1001 2
b111 B
b111 .
b111 D
b110 C
05
b110 0
b110 1
b110 E
1F
1-
#900
0F
0-
#950
03
07
04
b1000 2
b11 B
b11 .
b11 D
b111 C
15
b111 0
b111 1
b111 E
1F
1-
#1000
0F
0-
#1050
0>
0@
1A
1:
1?
1<
0=
16
1;
18
09
13
17
14
b111 2
b1 B
b1 .
b1 D
b0 C
05
b1000 0
b1000 1
b1000 E
1F
1-
#1100
0F
0-
#1150
03
07
04
b110 2
b0 B
b0 .
b0 D
b1 C
15
b1001 0
b1001 1
b1001 E
1F
1-
#1200
0F
0-
#1250
06
0;
08
19
13
17
14
b101 2
b1000 B
b1000 .
b1000 D
b10 C
05
b1010 0
b1010 1
b1010 E
1F
1-
#1300
0F
0-
#1350
03
07
04
b100 2
b1100 B
b1100 .
b1100 D
b11 C
15
b1011 0
b1011 1
b1011 E
1F
1-
#1400
0F
0-
#1450
0:
0?
0<
1=
16
1;
18
09
13
17
14
b11 2
b1110 B
b1110 .
b1110 D
b100 C
05
b1100 0
b1100 1
b1100 E
1F
1-
#1500
0F
0-
#1550
03
07
04
b10 2
b1111 B
b1111 .
b1111 D
b101 C
15
b1101 0
b1101 1
b1101 E
1F
1-
#1600
0F
0-
#1650
06
0;
08
19
13
17
14
b1 2
b111 B
b111 .
b111 D
b110 C
05
b1110 0
b1110 1
b1110 E
1F
1-
#1700
0F
0-
#1750
03
07
04
b0 2
b11 B
b11 .
b11 D
b111 C
15
b1111 0
b1111 1
b1111 E
1F
1-
#1800
0F
0-
#1850
1>
1@
0A
1:
1?
1<
0=
16
1;
18
09
13
17
14
b1111 2
b1 B
b1 .
b1 D
b0 C
05
b0 0
b0 1
b0 E
1F
1-
#1900
0F
0-
#1950
03
07
04
b1110 2
b0 B
b0 .
b0 D
b1 C
15
b1 0
b1 1
b1 E
1F
1-
#2000
0F
0-
#2050
06
0;
08
19
13
17
14
b1101 2
b1000 B
b1000 .
b1000 D
b10 C
05
b10 0
b10 1
b10 E
1F
1-
#2100
0F
0-
#2150
03
07
04
b1100 2
b1100 B
b1100 .
b1100 D
b11 C
15
b11 0
b11 1
b11 E
1F
1-
#2200
0F
0-
#2250
0:
0?
0<
1=
16
1;
18
09
13
17
14
b1011 2
b1110 B
b1110 .
b1110 D
b100 C
05
b100 0
b100 1
b100 E
1F
1-
#2300
0F
0-
#2350
03
07
04
b1010 2
b1111 B
b1111 .
b1111 D
b101 C
15
b101 0
b101 1
b101 E
1F
1-
#2400
0F
0-
#2450
06
0;
08
19
13
17
14
b1001 2
b111 B
b111 .
b111 D
b110 C
05
b110 0
b110 1
b110 E
1F
1-
#2500
0F
0-
#2550
03
07
04
b1000 2
b11 B
b11 .
b11 D
b111 C
15
b111 0
b111 1
b111 E
1F
1-
#2600
0F
0-
#2650
0>
0@
1A
1:
1?
1<
0=
16
1;
18
09
13
17
14
b111 2
b1 B
b1 .
b1 D
b0 C
05
b1000 0
b1000 1
b1000 E
1F
1-
#2700
0F
0-
#2750
03
07
04
b110 2
b0 B
b0 .
b0 D
b1 C
15
b1001 0
b1001 1
b1001 E
1F
1-
#2800
0F
0-
#2850
06
0;
08
19
13
17
14
b101 2
b1000 B
b1000 .
b1000 D
b10 C
05
b1010 0
b1010 1
b1010 E
1F
1-
#2900
0F
0-
#2950
03
07
04
b100 2
b1100 B
b1100 .
b1100 D
b11 C
15
b1011 0
b1011 1
b1011 E
1F
1-
#3000
0F
0-
#3050
0:
0?
0<
1=
16
1;
18
09
13
17
14
b11 2
b1110 B
b1110 .
b1110 D
b100 C
05
b1100 0
b1100 1
b1100 E
1F
1-
#3100
0F
0-
#3150
03
07
04
b10 2
b1111 B
b1111 .
b1111 D
b101 C
15
b1101 0
b1101 1
b1101 E
1F
1-
#3200
0F
0-
#3250
06
0;
08
19
13
17
14
b1 2
b111 B
b111 .
b111 D
b110 C
05
b1110 0
b1110 1
b1110 E
1F
1-
#3300
0F
0-
#3350
03
07
04
b0 2
b11 B
b11 .
b11 D
b111 C
15
b1111 0
b1111 1
b1111 E
1F
1-
