Lab1/DFlipFlop.v
module DFlipFlop(clk, reset, D, q, qBar);
   input D, clk, reset;
   output q, qBar;
   reg q;

   not n1 (qBar, q);

   always @ (negedge reset or posedge clk)
      begin
         if(!reset)
            q = 0;
         else
            q = D;
      end
endmodule

Lab1/SchemEntryCounter.v
// Copyright (C) 1991-2016 Altera Corporation. All rights reserved.
// Your use of Altera Corporation's design tools, logic functions 
// and other software and tools, and its AMPP partner logic 
// functions, and any output files from any of the foregoing 
// (including device programming or simulation files), and any 
// associated documentation or information are expressly subject 
// to the terms and conditions of the Altera Program License 
// Subscription Agreement, the Altera Quartus Prime License Agreement,
// the Altera MegaCore Function License Agreement, or other 
// applicable license agreement, including, without limitation, 
// that your use is for the sole purpose of programming logic 
// devices manufactured by Altera and sold by Altera or its 
// authorized distributors.  Please refer to the applicable 
// agreement for further details.

// PROGRAM		"Quartus Prime"
// VERSION		"Version 16.0.0 Build 211 04/27/2016 SJ Standard Edition"
// CREATED		"Fri Apr 14 15:47:16 2017"

module SchemEntryCounter(
	clk,
	reset,
	out1,
	out2,
	out3,
	out4
);


input wire	clk;
input wire	reset;
output wire	out1;
output wire	out2;
output wire	out3;
output wire	out4;

wire	SYNTHESIZED_WIRE_0;
wire	SYNTHESIZED_WIRE_1;
wire	SYNTHESIZED_WIRE_2;
wire	SYNTHESIZED_WIRE_3;
wire	SYNTHESIZED_WIRE_15;
wire	SYNTHESIZED_WIRE_16;
wire	SYNTHESIZED_WIRE_17;
wire	SYNTHESIZED_WIRE_18;
wire	SYNTHESIZED_WIRE_8;
wire	SYNTHESIZED_WIRE_9;

assign	out1 = SYNTHESIZED_WIRE_15;
assign	out2 = SYNTHESIZED_WIRE_16;
assign	out3 = SYNTHESIZED_WIRE_18;
assign	out4 = SYNTHESIZED_WIRE_9;




DFlipFlop	b2v_inst(
	.D(SYNTHESIZED_WIRE_0),
	.clk(clk),
	.reset(reset),
	.q(SYNTHESIZED_WIRE_15)
	);


DFlipFlop	b2v_inst1(
	.D(SYNTHESIZED_WIRE_1),
	.clk(clk),
	.reset(reset),
	.q(SYNTHESIZED_WIRE_16)
	);


DFlipFlop	b2v_inst2(
	.D(SYNTHESIZED_WIRE_2),
	.clk(clk),
	.reset(reset),
	.q(SYNTHESIZED_WIRE_18)
	);


DFlipFlop	b2v_inst3(
	.D(SYNTHESIZED_WIRE_3),
	.clk(clk),
	.reset(reset),
	.q(SYNTHESIZED_WIRE_9)
	);

assign	SYNTHESIZED_WIRE_1 = SYNTHESIZED_WIRE_15 ^ SYNTHESIZED_WIRE_16;

assign	SYNTHESIZED_WIRE_2 = SYNTHESIZED_WIRE_17 ^ SYNTHESIZED_WIRE_18;

assign	SYNTHESIZED_WIRE_3 = SYNTHESIZED_WIRE_8 ^ SYNTHESIZED_WIRE_9;

assign	SYNTHESIZED_WIRE_17 = SYNTHESIZED_WIRE_15 & SYNTHESIZED_WIRE_16;

assign	SYNTHESIZED_WIRE_8 = SYNTHESIZED_WIRE_17 & SYNTHESIZED_WIRE_18;

assign	SYNTHESIZED_WIRE_0 =  ~SYNTHESIZED_WIRE_15;


endmodule

Lab1/johnsonCounter.v
module johnsonCounter(clk, reset, count);
   input clk, reset;
   output reg [3:0] count;

   integer ps, ns;
      
   always @ (posedge clk)
      if (~reset)
         ps <= 0;
      else
         case (ps)
         0: begin
               ps = 1;
               count = 4'b0000;
            end
         1: begin
               ps = 2;
               count = 4'b1000;
               end
         2: begin
               ps = 3;
               count = 4'b1100;
            end
         3: begin
               ps = 4;
               count = 4'b1110;
            end
         4: begin
               ps = 5;
               count = 4'b1111;
            end
         5: begin
               ps = 6;
               count = 4'b0111;
            end
         6: begin
               ps = 7;
               count = 4'b0011;
            end
         7: begin
               ps = 0;
               count = 4'b0001;
            end
      endcase

endmodule

Lab1/syncrocounter.v
// A four stage (4 bit) synchronous up counter, with active low reset.
	//a. Design the counter using a dataflow model.
	//b. Use the D flip-flop model in the adjacent listing.
module syncrocounter (clk, reset, next);
	input clk, reset;
	wire [3:0] curr, qBar;
	output [3:0] next;
	
	assign next[0] = ~curr[0];
	assign next[1] = curr[0]^curr[1];
	assign next[2] = curr[2]^(curr[1] & curr[0]);
	assign next[3] = curr[3]^(curr[2] & curr[1] & curr[0]);
	
	DFlipFlop bit0(.clk(clk), .reset(reset), .D(next[0]), .q(curr[0]), .qBar(qBar[0]));
	DFlipFlop bit1(.clk(clk), .reset(reset), .D(next[1]), .q(curr[1]), .qBar(qBar[0]));
	DFlipFlop bit2(.clk(clk), .reset(reset), .D(next[2]), .q(curr[2]), .qBar(qBar[0]));
	DFlipFlop bit3(.clk(clk), .reset(reset), .D(next[3]), .q(curr[3]), .qBar(qBar[0]));
endmodule

Lab1/rippleCounter.v
`include "DFlipFlop.v"

// A four stage (4 bit) ripple up (asynchronous) counter, with active low reset.
//a. Design the counter using a gate or structural model.
//b. Use the D flip-flop model in the adjacent listing.
module rippleCounter(clk, reset, count);
   input clk, reset;
   output [3:0] count;
   wire   [3:0] countbar;
	
   DFlipFlop bit0(.clk(clk), .reset(reset), .D(countbar[0]), .q(count[0]), .qBar(countbar[0]));
   DFlipFlop bit1(.clk(countbar[0]), .reset(reset), .D(countbar[1]), .q(count[1]), .qBar(countbar[1]));
   DFlipFlop bit2(.clk(countbar[1]), .reset(reset), .D(countbar[2]), .q(count[2]), .qBar(countbar[2]));
   DFlipFlop bit3(.clk(countbar[2]), .reset(reset), .D(countbar[3]), .q(count[3]), .qBar(countbar[3]));

endmodule

Lab1/DE1_SoC.v
`include "rippleCounter.v"
`include "johnsonCounter.v"
`include "syncrocounter.v"
`include "SchemEntryCounter.v"

module DE1_SoC (CLOCK_50, HEX0, HEX1, HEX2, HEX3, HEX4, HEX5, KEY, LEDR,
SW); 
	input 		 CLOCK_50; // 50MHz clock.
	input  [3:0] KEY; // True when not pressed, False when pressed
	input  [9:0] SW;	
	output [6:0] HEX0, HEX1, HEX2, HEX3, HEX4, HEX5;
	output [9:0] LEDR;
	
	// Generate clk off of CLOCK_50, whichClock picks rate.
	wire [31:0] clk;
	parameter whichClock = 25;
	clock_divider cdiv (CLOCK_50, clk);

endmodule
		
	//	A four stage (4 bit) synchronous Johnson up counter, with active low reset
		//a. Design the counter using a behavioural model.
		
	// A four stage (4 bit) synchronous up counter, with active low reset, using schematic entry.	
 

//divided_clocks[0] = 25MHz, [1] = 12.5Mhz, ... [23] = 3Hz, [24] = 1.5Hz,[25] = 0.75Hz, ...
module clock_divider (clock, divided_clocks);
	input clock;
	output reg [31:0] divided_clocks;
	
	initial
		divided_clocks <= 0;
	always @(posedge clock)
		divided_clocks <= divided_clocks + 1;
endmodule

module counterTestBench;
	wire clk, reset;
	wire[3:0] rippleCount, johnsonCount, syncroCount, schemCount;
	
	rippleCounter rCounter (clk, reset, rippleCount);
	syncrocounter synCounter (clk, reset, syncroCount);
	johnsonCounter jCounter (clk, reset, johnsonCount);
	SchemEntryCounter schemCounter (.reset(reset), .clk(clk), .out1(schemCount[0]), .out2(schemCount[1]), .out3(schemCount[2]), .out4(schemCount[3]));
	
	Tester test(rippleCount, johnsonCount, syncroCount, schemCount, clk, reset);
	
	
	initial begin
		$dumpfile("counterTesterLog.vcd");
		$dumpvars;
	end
endmodule
	
module Tester(rippleCount, johnsonCount, syncroCount, schemCount, clk, reset);
	input [3:0] rippleCount, johnsonCount, syncroCount, schemCount;
	output clk, reset;
	reg clk, reset;
	
	initial begin
		$display("\t\t clk \t reset \t rippleCount \t johnsonCount \t syncroCount \t schemCount");
		$monitor("\t\t %b  \t %b    \t %b          \t %b           \t %b          \t %b", 
			     clk, reset, rippleCount, johnsonCount, syncroCount, schemCount);
	end
	
	parameter CLOCK = 100;
	
	initial begin
		clk <= 0;
		forever #(CLOCK/2) clk <= ~clk;
	end

	initial begin @(posedge clk)
		reset <= 0; @(posedge clk)@(posedge clk)
		reset <= 1; @(posedge clk)@(posedge clk)
		repeat(30)@(posedge clk);
		$stop;
	end
	

endmodule

Lab1/counterTesterLog.vcd
$date
	Fri Apr 14 15:53:35 2017
$end
$version
	Icarus Verilog
$end
$timescale
	1s
$end
$scope module DE1_SoC $end
$var wire 1 ! CLOCK_50 $end
$var wire 7 " HEX0 [6:0] $end
$var wire 7 # HEX1 [6:0] $end
$var wire 7 $ HEX2 [6:0] $end
$var wire 7 % HEX3 [6:0] $end
$var wire 7 & HEX4 [6:0] $end
$var wire 7 ' HEX5 [6:0] $end
$var wire 4 ( KEY [3:0] $end
$var wire 10 ) LEDR [9:0] $end
$var wire 10 * SW [9:0] $end
$var wire 32 + clk [31:0] $end
$scope module cdiv $end
$var wire 1 ! clock $end
$var reg 32 , divided_clocks [31:0] $end
$upscope $end
$upscope $end
$scope module counterTestBench $end
$var wire 1 - clk $end
$var wire 4 . johnsonCount [3:0] $end
$var wire 1 / reset $end
$var wire 4 0 rippleCount [3:0] $end
$var wire 4 1 schemCount [3:0] $end
$var wire 4 2 syncroCount [3:0] $end
$scope module rCounter $end
$var wire 1 - clk $end
$var wire 4 3 count [3:0] $end
$var wire 4 4 countbar [3:0] $end
$var wire 1 / reset $end
$scope module bit0 $end
$var wire 1 5 D $end
$var wire 1 - clk $end
$var wire 1 6 qBar $end
$var wire 1 / reset $end
$var reg 1 7 q $end
$upscope $end
$scope module bit1 $end
$var wire 1 8 D $end
$var wire 1 9 clk $end
$var wire 1 : qBar $end
$var wire 1 / reset $end
$var reg 1 ; q $end
$upscope $end
$scope module bit2 $end
$var wire 1 < D $end
$var wire 1 = clk $end
$var wire 1 > qBar $end
$var wire 1 / reset $end
$var reg 1 ? q $end
$upscope $end
$scope module bit3 $end
$var wire 1 @ D $end
$var wire 1 A clk $end
$var wire 1 B qBar $end
$var wire 1 / reset $end
$var reg 1 C q $end
$upscope $end
$upscope $end
$scope module synCounter $end
$var wire 1 - clk $end
$var wire 4 D curr [3:0] $end
$var wire 4 E next [3:0] $end
$var wire 4 F qBar [3:0] $end
$var wire 1 / reset $end
$scope module bit0 $end
$var wire 1 G D $end
$var wire 1 - clk $end
$var wire 1 H qBar $end
$var wire 1 / reset $end
$var reg 1 I q $end
$upscope $end
$scope module bit1 $end
$var wire 1 J D $end
$var wire 1 - clk $end
$var wire 1 K qBar $end
$var wire 1 / reset $end
$var reg 1 L q $end
$upscope $end
$scope module bit2 $end
$var wire 1 M D $end
$var wire 1 - clk $end
$var wire 1 N qBar $end
$var wire 1 / reset $end
$var reg 1 O q $end
$upscope $end
$scope module bit3 $end
$var wire 1 P D $end
$var wire 1 - clk $end
$var wire 1 Q qBar $end
$var wire 1 / reset $end
$var reg 1 R q $end
$upscope $end
$upscope $end
$scope module jCounter $end
$var wire 1 - clk $end
$var wire 1 / reset $end
$var reg 4 S count [3:0] $end
$var integer 32 T ps [31:0] $end
$upscope $end
$scope module schemCounter $end
$var wire 1 U SYNTHESIZED_WIRE_0 $end
$var wire 1 V SYNTHESIZED_WIRE_1 $end
$var wire 1 W SYNTHESIZED_WIRE_15 $end
$var wire 1 X SYNTHESIZED_WIRE_16 $end
$var wire 1 Y SYNTHESIZED_WIRE_17 $end
$var wire 1 Z SYNTHESIZED_WIRE_18 $end
$var wire 1 [ SYNTHESIZED_WIRE_2 $end
$var wire 1 \ SYNTHESIZED_WIRE_3 $end
$var wire 1 ] SYNTHESIZED_WIRE_8 $end
$var wire 1 ^ SYNTHESIZED_WIRE_9 $end
$var wire 1 - clk $end
$var wire 1 _ out1 $end
$var wire 1 ` out2 $end
$var wire 1 a out3 $end
$var wire 1 b out4 $end
$var wire 1 / reset $end
$scope module b2v_inst $end
$var wire 1 U D $end
$var wire 1 - clk $end
$var wire 1 c qBar $end
$var wire 1 / reset $end
$var reg 1 d q $end
$upscope $end
$scope module b2v_inst1 $end
$var wire 1 V D $end
$var wire 1 - clk $end
$var wire 1 e qBar $end
$var wire 1 / reset $end
$var reg 1 f q $end
$upscope $end
$scope module b2v_inst2 $end
$var wire 1 [ D $end
$var wire 1 - clk $end
$var wire 1 g qBar $end
$var wire 1 / reset $end
$var reg 1 h q $end
$upscope $end
$scope module b2v_inst3 $end
$var wire 1 \ D $end
$var wire 1 - clk $end
$var wire 1 i qBar $end
$var wire 1 / reset $end
$var reg 1 j q $end
$upscope $end
$upscope $end
$scope module test $end
$var wire 4 k johnsonCount [3:0] $end
$var wire 4 l rippleCount [3:0] $end
$var wire 4 m schemCount [3:0] $end
$var wire 4 n syncroCount [3:0] $end
$var reg 1 o clk $end
$var reg 1 p reset $end
$upscope $end
$upscope $end
$enddefinitions $end
#0
$dumpvars
xp
0o
bx n
bx m
bx l
bx k
xj
xi
xh
xg
xf
xe
xd
xc
xb
xa
x`
x_
x^
x]
x\
x[
xZ
xY
xX
xW
xV
xU
bx T
bx S
xR
xQ
xP
xO
xN
xM
xL
xK
xJ
xI
xH
xG
bzx F
bx E
bx D
xC
xB
xA
x@
x?
x>
x=
x<
x;
x:
x9
x8
x7
x6
x5
bx 4
bx 3
bx 2
bx 1
bx 0
x/
bx .
0-
b0 ,
b0 +
bz *
bz )
bz (
bz '
bz &
bz %
bz $
bz #
bz "
z!
$end
#50
0P
0M
1G
0J
b1 2
b1 E
b1 n
15
19
1@
1<
1A
18
1=
1i
0\
1g
0]
0[
1e
1c
1U
0Y
0V
1Q
bz1 F
1N
1K
1H
16
1B
1>
1:
b1111 4
0j
0^
0b
0h
0Z
0a
0f
0X
0`
0d
0W
0_
b0 1
b0 m
0R
0O
0L
0I
b0 D
07
0C
0?
0;
b0 0
b0 3
b0 l
0p
0/
1o
1-
#100
0o
0-
#150
b0 T
1o
1-
#200
0o
0-
#250
1p
1/
1o
1-
#300
0o
0-
#350
0G
1J
05
09
b10 2
b10 E
b10 n
06
b1110 4
0H
bzx F
0c
0U
1V
b0 S
b0 .
b0 k
b1 T
17
b1 0
b1 3
b1 l
1I
b1 D
1d
1W
1_
b1 1
b1 m
1o
1-
#400
0o
0-
#450
08
0=
0:
1G
1;
b11 2
b11 E
b11 n
15
19
0e
1c
1U
0K
1H
bzx F
16
b1101 4
b1000 S
b1000 .
b1000 k
b10 T
1f
1X
1`
0d
0W
0_
b10 1
b10 m
1L
0I
b10 D
07
b10 0
b10 3
b10 l
1o
1-
#500
0o
0-
#550
1M
0G
0J
05
09
b100 2
b100 E
b100 n
1[
06
b1100 4
0H
0c
0U
1Y
0V
b1100 S
b1100 .
b1100 k
b11 T
17
b11 0
b11 3
b11 l
1I
b11 D
1d
1W
1_
b11 1
b11 m
1o
1-
#600
0o
0-
#650
0<
0A
0>
1?
18
1=
1:
1G
0;
b101 2
b101 E
b101 n
15
19
0g
1e
1c
1U
0Y
0N
1K
bzx F
1H
16
b1011 4
b1110 S
b1110 .
b1110 k
b100 T
1h
1Z
1a
0f
0X
0`
0d
0W
0_
b100 1
b100 m
1O
0L
0I
b100 D
07
b100 0
b100 3
b100 l
1o
1-
#700
0o
0-
#750
0G
1J
05
09
b110 2
b110 E
b110 n
06
b1010 4
0H
0c
0U
1V
b1111 S
b1111 .
b1111 k
b101 T
17
b101 0
b101 3
b101 l
1I
b101 D
1d
1W
1_
b101 1
b101 m
1o
1-
#800
0o
0-
#850
08
0=
0:
1G
1;
b111 2
b111 E
b111 n
15
19
0e
1c
1U
0K
1H
16
b1001 4
b111 S
b111 .
b111 k
b110 T
1f
1X
1`
0d
0W
0_
b110 1
b110 m
1L
0I
b110 D
07
b110 0
b110 3
b110 l
1o
1-
#900
0o
0-
#950
0M
1P
0G
0J
1\
05
09
b1000 2
b1000 E
b1000 n
1]
0[
06
b1000 4
0H
0c
0U
1Y
0V
b11 S
b11 .
b11 k
b111 T
17
b111 0
b111 3
b111 l
1I
b111 D
1d
1W
1_
b111 1
b111 m
1o
1-
#1000
0o
0-
#1050
0@
0B
1C
1<
1A
1>
0?
18
1=
1:
1G
0;
b1001 2
b1001 E
b1001 n
15
19
0i
1g
0]
1e
1c
1U
0Y
0Q
1N
bzx F
1K
1H
16
b111 4
b1 S
b1 .
b1 k
b0 T
1j
1^
1b
0h
0Z
0a
0f
0X
0`
0d
0W
0_
b1000 1
b1000 m
1R
0O
0L
0I
b1000 D
07
b1000 0
b1000 3
b1000 l
1o
1-
#1100
0o
0-
#1150
0G
1J
05
09
b1010 2
b1010 E
b1010 n
06
b110 4
0H
0c
0U
1V
b0 S
b0 .
b0 k
b1 T
17
b1001 0
b1001 3
b1001 l
1I
b1001 D
1d
1W
1_
b1001 1
b1001 m
1o
1-
#1200
0o
0-
#1250
08
0=
0:
1G
1;
b1011 2
b1011 E
b1011 n
15
19
0e
1c
1U
0K
1H
16
b101 4
b1000 S
b1000 .
b1000 k
b10 T
1f
1X
1`
0d
0W
0_
b1010 1
b1010 m
1L
0I
b1010 D
07
b1010 0
b1010 3
b1010 l
1o
1-
#1300
0o
0-
#1350
1M
0G
0J
05
09
b1100 2
b1100 E
b1100 n
1[
06
b100 4
0H
0c
0U
1Y
0V
b1100 S
b1100 .
b1100 k
b11 T
17
b1011 0
b1011 3
b1011 l
1I
b1011 D
1d
1W
1_
b1011 1
b1011 m
1o
1-
#1400
0o
0-
#1450
0<
0A
0>
1?
18
1=
1:
1G
0;
b1101 2
b1101 E
b1101 n
15
19
0g
1e
1c
1U
0Y
0N
1K
1H
16
b11 4
b1110 S
b1110 .
b1110 k
b100 T
1h
1Z
1a
0f
0X
0`
0d
0W
0_
b1100 1
b1100 m
1O
0L
0I
b1100 D
07
b1100 0
b1100 3
b1100 l
1o
1-
#1500
0o
0-
#1550
0G
1J
05
09
b1110 2
b1110 E
b1110 n
06
b10 4
0H
0c
0U
1V
b1111 S
b1111 .
b1111 k
b101 T
17
b1101 0
b1101 3
b1101 l
1I
b1101 D
1d
1W
1_
b1101 1
b1101 m
1o
1-
#1600
0o
0-
#1650
08
0=
0:
1G
1;
b1111 2
b1111 E
b1111 n
15
19
0e
1c
1U
0K
1H
16
b1 4
b111 S
b111 .
b111 k
b110 T
1f
1X
1`
0d
0W
0_
b1110 1
b1110 m
1L
0I
b1110 D
07
b1110 0
b1110 3
b1110 l
1o
1-
#1700
0o
0-
#1750
0M
0P
0G
0J
0\
05
09
b0 2
b0 E
b0 n
1]
0[
06
b0 4
0H
bz0 F
0c
0U
1Y
0V
b11 S
b11 .
b11 k
b111 T
17
b1111 0
b1111 3
b1111 l
1I
b1111 D
1d
1W
1_
b1111 1
b1111 m
1o
1-
#1800
0o
0-
#1850
1@
1B
0C
1<
1A
1>
0?
18
1=
1:
1G
0;
b1 2
b1 E
b1 n
15
19
1i
1g
0]
1e
1c
1U
0Y
1Q
1N
1K
1H
bz1 F
16
b1111 4
b1 S
b1 .
b1 k
b0 T
0j
0^
0b
0h
0Z
0a
0f
0X
0`
0d
0W
0_
b0 1
b0 m
0R
0O
0L
0I
b0 D
07
b0 0
b0 3
b0 l
1o
1-
#1900
0o
0-
#1950
0G
1J
05
09
b10 2
b10 E
b10 n
06
b1110 4
0H
bzx F
0c
0U
1V
b0 S
b0 .
b0 k
b1 T
17
b1 0
b1 3
b1 l
1I
b1 D
1d
1W
1_
b1 1
b1 m
1o
1-
#2000
0o
0-
#2050
08
0=
0:
1G
1;
b11 2
b11 E
b11 n
15
19
0e
1c
1U
0K
1H
bzx F
16
b1101 4
b1000 S
b1000 .
b1000 k
b10 T
1f
1X
1`
0d
0W
0_
b10 1
b10 m
1L
0I
b10 D
07
b10 0
b10 3
b10 l
1o
1-
#2100
0o
0-
#2150
1M
0G
0J
05
09
b100 2
b100 E
b100 n
1[
06
b1100 4
0H
0c
0U
1Y
0V
b1100 S
b1100 .
b1100 k
b11 T
17
b11 0
b11 3
b11 l
1I
b11 D
1d
1W
1_
b11 1
b11 m
1o
1-
#2200
0o
0-
#2250
0<
0A
0>
1?
18
1=
1:
1G
0;
b101 2
b101 E
b101 n
15
19
0g
1e
1c
1U
0Y
0N
1K
bzx F
1H
16
b1011 4
b1110 S
b1110 .
b1110 k
b100 T
1h
1Z
1a
0f
0X
0`
0d
0W
0_
b100 1
b100 m
1O
0L
0I
b100 D
07
b100 0
b100 3
b100 l
1o
1-
#2300
0o
0-
#2350
0G
1J
05
09
b110 2
b110 E
b110 n
06
b1010 4
0H
0c
0U
1V
b1111 S
b1111 .
b1111 k
b101 T
17
b101 0
b101 3
b101 l
1I
b101 D
1d
1W
1_
b101 1
b101 m
1o
1-
#2400
0o
0-
#2450
08
0=
0:
1G
1;
b111 2
b111 E
b111 n
15
19
0e
1c
1U
0K
1H
16
b1001 4
b111 S
b111 .
b111 k
b110 T
1f
1X
1`
0d
0W
0_
b110 1
b110 m
1L
0I
b110 D
07
b110 0
b110 3
b110 l
1o
1-
#2500
0o
0-
#2550
0M
1P
0G
0J
1\
05
09
b1000 2
b1000 E
b1000 n
1]
0[
06
b1000 4
0H
0c
0U
1Y
0V
b11 S
b11 .
b11 k
b111 T
17
b111 0
b111 3
b111 l
1I
b111 D
1d
1W
1_
b111 1
b111 m
1o
1-
#2600
0o
0-
#2650
0@
0B
1C
1<
1A
1>
0?
18
1=
1:
1G
0;
b1001 2
b1001 E
b1001 n
15
19
0i
1g
0]
1e
1c
1U
0Y
0Q
1N
bzx F
1K
1H
16
b111 4
b1 S
b1 .
b1 k
b0 T
1j
1^
1b
0h
0Z
0a
0f
0X
0`
0d
0W
0_
b1000 1
b1000 m
1R
0O
0L
0I
b1000 D
07
b1000 0
b1000 3
b1000 l
1o
1-
#2700
0o
0-
#2750
0G
1J
05
09
b1010 2
b1010 E
b1010 n
06
b110 4
0H
0c
0U
1V
b0 S
b0 .
b0 k
b1 T
17
b1001 0
b1001 3
b1001 l
1I
b1001 D
1d
1W
1_
b1001 1
b1001 m
1o
1-
#2800
0o
0-
#2850
08
0=
0:
1G
1;
b1011 2
b1011 E
b1011 n
15
19
0e
1c
1U
0K
1H
16
b101 4
b1000 S
b1000 .
b1000 k
b10 T
1f
1X
1`
0d
0W
0_
b1010 1
b1010 m
1L
0I
b1010 D
07
b1010 0
b1010 3
b1010 l
1o
1-
#2900
0o
0-
#2950
1M
0G
0J
05
09
b1100 2
b1100 E
b1100 n
1[
06
b100 4
0H
0c
0U
1Y
0V
b1100 S
b1100 .
b1100 k
b11 T
17
b1011 0
b1011 3
b1011 l
1I
b1011 D
1d
1W
1_
b1011 1
b1011 m
1o
1-
#3000
0o
0-
#3050
0<
0A
0>
1?
18
1=
1:
1G
0;
b1101 2
b1101 E
b1101 n
15
19
0g
1e
1c
1U
0Y
0N
1K
1H
16
b11 4
b1110 S
b1110 .
b1110 k
b100 T
1h
1Z
1a
0f
0X
0`
0d
0W
0_
b1100 1
b1100 m
1O
0L
0I
b1100 D
07
b1100 0
b1100 3
b1100 l
1o
1-
#3100
0o
0-
#3150
0G
1J
05
09
b1110 2
b1110 E
b1110 n
06
b10 4
0H
0c
0U
1V
b1111 S
b1111 .
b1111 k
b101 T
17
b1101 0
b1101 3
b1101 l
1I
b1101 D
1d
1W
1_
b1101 1
b1101 m
1o
1-
#3200
0o
0-
#3250
08
0=
0:
1G
1;
b1111 2
b1111 E
b1111 n
15
19
0e
1c
1U
0K
1H
16
b1 4
b111 S
b111 .
b111 k
b110 T
1f
1X
1`
0d
0W
0_
b1110 1
b1110 m
1L
0I
b1110 D
07
b1110 0
b1110 3
b1110 l
1o
1-
#3300
0o
0-
#3350
0M
0P
0G
0J
0\
05
09
b0 2
b0 E
b0 n
1]
0[
06
b0 4
0H
bz0 F
0c
0U
1Y
0V
b11 S
b11 .
b11 k
b111 T
17
b1111 0
b1111 3
b1111 l
1I
b1111 D
1d
1W
1_
b1111 1
b1111 m
1o
1-
